snp/__init__.py
snp/construct_w.py
snp/dgcv.py
snp/snp.py
snp_nw-0.1.2.dist-info/licenses/LICENSE
snp_nw-0.1.2.dist-info/METADATA
snp_nw-0.1.2.dist-info/WHEEL
snp_nw-0.1.2.dist-info/top_level.txt
snp_nw-0.1.2.dist-info/RECORD
