Metadata-Version: 2.4
Name: snp-nw
Version: 0.1.2
Summary: Stepwise Noise Peeling (SNP) for Nadaraya–Watson Regression
Author: Bistoon Hosseini
License: MIT License
Requires-Python: >=3.8
License-File: LICENSE
Requires-Dist: numpy>=1.21
Dynamic: license-file
